MANIFEST.in
README.rst
setup.py
StarClusterExtensions.egg-info/PKG-INFO
StarClusterExtensions.egg-info/SOURCES.txt
StarClusterExtensions.egg-info/dependency_links.txt
StarClusterExtensions.egg-info/requires.txt
StarClusterExtensions.egg-info/top_level.txt
bin/sce
sce/__init__.py
sce/plugins/__init__.py
sce/plugins/genomekey/__init__.py
sce/plugins/genomekey/plugin.py
sce/plugins/genomekey/util.py
sce/plugins/genomekey/fab/__init__.py
sce/plugins/genomekey/fab/aws.py
sce/plugins/genomekey/fab/gk.py
sce/plugins/genomekey/fab/util.py
sce/plugins/gluster/__init__.py
sce/plugins/gluster/gluster.py
sce/plugins/gluster/plugin.py
sce/plugins/sge_plus/__init__.py
sce/plugins/sge_plus/plugin.py
sce/plugins/sge_plus/data/msconf
sce/plugins/sge_plus/data/qconf_c
sce/utils/__init__.py
sce/utils/misc.py
sce/utils/node.py
sce/utils/plugin.py
sce/utils/shell.py