Metadata-Version: 1.0
Name: StarClusterExtensions
Version: 0.3.7
Summary: StarCluster Extensions
Home-page: UNKNOWN
Author: Erik Gafni
Author-email: UNKNOWN
License: MIT
Platform: UNKNOWN
